ptnmap/__init__.py
ptnmap/_version.py
ptnmap/ptnmap.py
ptnmap/modules/__init__.py
ptnmap/modules/xml_parser.py
ptnmap-0.0.3.dist-info/LICENSE
ptnmap-0.0.3.dist-info/METADATA
ptnmap-0.0.3.dist-info/WHEEL
ptnmap-0.0.3.dist-info/entry_points.txt
ptnmap-0.0.3.dist-info/top_level.txt
ptnmap-0.0.3.dist-info/RECORD
