Metadata-Version: 2.1
Name: ptnmap
Version: 0.0.3
Summary: ptnmap
Home-page: https://www.penterep.com/
Author: Penterep
Author-email: info@penterep.com
License: GPLv3
Project-URL: homepage, https://www.penterep.com/
Project-URL: repository, https://github.com/penterep/ptnmap
Project-URL: tracker, https://github.com/penterep/ptnmap/issues
Project-URL: changelog, https://github.com/penterep/ptnmap/blob/main/CHANGELOG.md
Classifier: Programming Language :: Python :: 3
Classifier: Programming Language :: Python :: Implementation :: CPython
Classifier: Environment :: Console
Classifier: Topic :: Security
Classifier: License :: OSI Approved :: GNU General Public License v3 (GPLv3)
Requires-Python: >=3.9
License-File: LICENSE
Requires-Dist: ptlibs <2,>=1.0.7
Requires-Dist: defusedxml
